ftlid/__init__.py
ftlid/lid.176.ftz
ftlid-0.1.2.dist-info/LICENSE
ftlid-0.1.2.dist-info/WHEEL
ftlid-0.1.2.dist-info/METADATA
ftlid-0.1.2.dist-info/RECORD
