Metadata-Version: 2.1
Name: ftlid
Version: 0.1.2
Summary: A small and fast language identification model powered by fastText
License: MIT
Author: Marek Suppa
Author-email: mr@shu.io
Requires-Python: >=3.6,<4.0
Classifier: License :: OSI Approved :: MIT License
Classifier: Programming Language :: Python :: 3
Classifier: Programming Language :: Python :: 3.6
Classifier: Programming Language :: Python :: 3.7
Requires-Dist: fasttext (>=0.9.1,<0.10.0)
